[
  {
    "cardId": "1-4-001",
    "hp": 187,
    "atk": 146,
    "def_": 146,
    "spAtk": 182,
    "spDef": 123,
    "spd": 111
  },
  {
    "cardId": "1-4-002",
    "hp": 33,
    "atk": 175,
    "def_": 13,
    "spAtk": 146,
    "spDef": 123,
    "spd": 182
  },
  {
    "cardId": "1-4-003",
    "hp": 217,
    "atk": 159,
    "def_": 117,
    "spAtk": 159,
    "spDef": 120,
    "spd": 121
  },
  {
    "cardId": "1-4-004",
    "hp": 217,
    "atk": 159,
    "def_": 117,
    "spAtk": 159,
    "spDef": 120,
    "spd": 121
  },
  {
    "cardId": "1-4-005",
    "hp": 190,
    "atk": 203,
    "def_": 185,
    "spAtk": 107,
    "spDef": 161,
    "spd": 65
  },
  {
    "cardId": "1-4-006",
    "hp": 144,
    "atk": 144,
    "def_": 119,
    "spAtk": 119,
    "spDef": 119,
    "spd": 119
  },
  {
    "cardId": "1-4-007",
    "hp": 133,
    "atk": 111,
    "def_": 99,
    "spAtk": 64,
    "spDef": 128,
    "spd": 118
  },
  {
    "cardId": "1-4-008",
    "hp": 213,
    "atk": 144,
    "def_": 109,
    "spAtk": 202,
    "spDef": 121,
    "spd": 116
  },
  {
    "cardId": "1-4-009",
    "hp": 63,
    "atk": 63,
    "def_": 211,
    "spAtk": 211,
    "spDef": 211,
    "spd": 211
  },
  {
    "cardId": "1-4-010",
    "hp": 196,
    "atk": 185,
    "def_": 113,
    "spAtk": 185,
    "spDef": 113,
    "spd": 119
  },
  {
    "cardId": "1-4-011",
    "hp": 142,
    "atk": 33,
    "def_": 126,
    "spAtk": 203,
    "spDef": 71,
    "spd": 71
  },
  {
    "cardId": "1-4-012",
    "hp": 142,
    "atk": 30,
    "def_": 88,
    "spAtk": 107,
    "spDef": 89,
    "spd": 107
  },
  {
    "cardId": "1-4-013",
    "hp": 140,
    "atk": 90,
    "def_": 84,
    "spAtk": 91,
    "spDef": 116,
    "spd": 107
  },
  {
    "cardId": "1-4-014",
    "hp": 147,
    "atk": 112,
    "def_": 107,
    "spAtk": 63,
    "spDef": 89,
    "spd": 85
  },
  {
    "cardId": "1-4-015",
    "hp": 37,
    "atk": 113,
    "def_": 80,
    "spAtk": 123,
    "spDef": 167,
    "spd": 91
  },
  {
    "cardId": "1-4-016",
    "hp": 172,
    "atk": 100,
    "def_": 120,
    "spAtk": 63,
    "spDef": 98,
    "spd": 78
  },
  {
    "cardId": "1-4-017",
    "hp": 124,
    "atk": 105,
    "def_": 158,
    "spAtk": 58,
    "spDef": 176,
    "spd": 36
  },
  {
    "cardId": "1-4-018",
    "hp": 165,
    "atk": 140,
    "def_": 88,
    "spAtk": 72,
    "spDef": 93,
    "spd": 62
  },
  {
    "cardId": "1-4-019",
    "hp": 139,
    "atk": 34,
    "def_": 76,
    "spAtk": 76,
    "spDef": 142,
    "spd": 131
  },
  {
    "cardId": "1-4-020",
    "hp": 168,
    "atk": 98,
    "def_": 110,
    "spAtk": 89,
    "spDef": 67,
    "spd": 103
  },
  {
    "cardId": "1-4-021",
    "hp": 160,
    "atk": 113,
    "def_": 59,
    "spAtk": 113,
    "spDef": 59,
    "spd": 221
  },
  {
    "cardId": "1-4-022",
    "hp": 280,
    "atk": 113,
    "def_": 59,
    "spAtk": 113,
    "spDef": 59,
    "spd": 91
  },
  {
    "cardId": "1-4-023",
    "hp": 161,
    "atk": 37,
    "def_": 125,
    "spAtk": 134,
    "spDef": 82,
    "spd": 80
  },
  {
    "cardId": "1-4-024",
    "hp": 185,
    "atk": 37,
    "def_": 63,
    "spAtk": 137,
    "spDef": 75,
    "spd": 86
  },
  {
    "cardId": "1-4-025",
    "hp": 143,
    "atk": 89,
    "def_": 78,
    "spAtk": 81,
    "spDef": 76,
    "spd": 136
  },
  {
    "cardId": "1-4-026",
    "hp": 127,
    "atk": 122,
    "def_": 80,
    "spAtk": 61,
    "spDef": 99,
    "spd": 84
  },
  {
    "cardId": "1-4-027",
    "hp": 165,
    "atk": 30,
    "def_": 141,
    "spAtk": 91,
    "spDef": 75,
    "spd": 85
  },
  {
    "cardId": "1-4-028",
    "hp": 40,
    "atk": 59,
    "def_": 30,
    "spAtk": 38,
    "spDef": 30,
    "spd": 38
  },
  {
    "cardId": "1-4-029",
    "hp": 87,
    "atk": 48,
    "def_": 61,
    "spAtk": 49,
    "spDef": 61,
    "spd": 47
  },
  {
    "cardId": "1-4-030",
    "hp": 176,
    "atk": 72,
    "def_": 87,
    "spAtk": 87,
    "spDef": 73,
    "spd": 70
  },
  {
    "cardId": "1-4-031",
    "hp": 56,
    "atk": 32,
    "def_": 27,
    "spAtk": 36,
    "spDef": 31,
    "spd": 38
  },
  {
    "cardId": "1-4-032",
    "hp": 85,
    "atk": 30,
    "def_": 49,
    "spAtk": 45,
    "spDef": 61,
    "spd": 50
  },
  {
    "cardId": "1-4-033",
    "hp": 114,
    "atk": 63,
    "def_": 73,
    "spAtk": 68,
    "spDef": 63,
    "spd": 94
  },
  {
    "cardId": "1-4-034",
    "hp": 62,
    "atk": 38,
    "def_": 38,
    "spAtk": 27,
    "spDef": 29,
    "spd": 27
  },
  {
    "cardId": "1-4-035",
    "hp": 54,
    "atk": 61,
    "def_": 61,
    "spAtk": 49,
    "spDef": 46,
    "spd": 45
  },
  {
    "cardId": "1-4-036",
    "hp": 120,
    "atk": 37,
    "def_": 91,
    "spAtk": 87,
    "spDef": 69,
    "spd": 73
  },
  {
    "cardId": "1-4-037",
    "hp": 50,
    "atk": 36,
    "def_": 20,
    "spAtk": 25,
    "spDef": 20,
    "spd": 47
  },
  {
    "cardId": "1-4-038",
    "hp": 97,
    "atk": 63,
    "def_": 64,
    "spAtk": 42,
    "spDef": 49,
    "spd": 42
  },
  {
    "cardId": "1-4-039",
    "hp": 144,
    "atk": 112,
    "def_": 112,
    "spAtk": 112,
    "spDef": 112,
    "spd": 108
  },
  {
    "cardId": "1-4-040",
    "hp": 56,
    "atk": 28,
    "def_": 28,
    "spAtk": 43,
    "spDef": 33,
    "spd": 31
  },
  {
    "cardId": "1-4-041",
    "hp": 140,
    "atk": 60,
    "def_": 60,
    "spAtk": 58,
    "spDef": 58,
    "spd": 58
  },
  {
    "cardId": "1-4-042",
    "hp": 37,
    "atk": 47,
    "def_": 64,
    "spAtk": 99,
    "spDef": 68,
    "spd": 30
  },
  {
    "cardId": "1-4-043",
    "hp": 59,
    "atk": 37,
    "def_": 24,
    "spAtk": 38,
    "spDef": 33,
    "spd": 54
  },
  {
    "cardId": "1-4-044",
    "hp": 95,
    "atk": 66,
    "def_": 47,
    "spAtk": 75,
    "spDef": 67,
    "spd": 82
  },
  {
    "cardId": "1-4-045",
    "hp": 117,
    "atk": 110,
    "def_": 62,
    "spAtk": 86,
    "spDef": 78,
    "spd": 86
  },
  {
    "cardId": "1-4-046",
    "hp": 13,
    "atk": 34,
    "def_": 33,
    "spAtk": 41,
    "spDef": 51,
    "spd": 51
  },
  {
    "cardId": "1-4-047",
    "hp": 113,
    "atk": 61,
    "def_": 68,
    "spAtk": 89,
    "spDef": 73,
    "spd": 96
  },
  {
    "cardId": "1-4-048",
    "hp": 57,
    "atk": 25,
    "def_": 33,
    "spAtk": 28,
    "spDef": 25,
    "spd": 29
  },
  {
    "cardId": "1-4-049",
    "hp": 110,
    "atk": 70,
    "def_": 87,
    "spAtk": 54,
    "spDef": 78,
    "spd": 77
  },
  {
    "cardId": "1-4-050",
    "hp": 63,
    "atk": 38,
    "def_": 31,
    "spAtk": 28,
    "spDef": 31,
    "spd": 24
  },
  {
    "cardId": "1-4-051",
    "hp": 100,
    "atk": 67,
    "def_": 56,
    "spAtk": 53,
    "spDef": 56,
    "spd": 47
  },
  {
    "cardId": "1-4-052",
    "hp": 132,
    "atk": 95,
    "def_": 82,
    "spAtk": 82,
    "spDef": 112,
    "spd": 89
  },
  {
    "cardId": "1-4-053",
    "hp": 69,
    "atk": 34,
    "def_": 28,
    "spAtk": 27,
    "spDef": 33,
    "spd": 27
  },
  {
    "cardId": "1-4-054",
    "hp": 34,
    "atk": 46,
    "def_": 44,
    "spAtk": 44,
    "spDef": 60,
    "spd": 87
  },
  {
    "cardId": "1-4-055",
    "hp": 72,
    "atk": 46,
    "def_": 31,
    "spAtk": 23,
    "spDef": 23,
    "spd": 23
  },
  {
    "cardId": "1-4-056",
    "hp": 103,
    "atk": 77,
    "def_": 55,
    "spAtk": 41,
    "spDef": 48,
    "spd": 37
  },
  {
    "cardId": "1-4-057",
    "hp": 127,
    "atk": 114,
    "def_": 72,
    "spAtk": 59,
    "spDef": 76,
    "spd": 51
  },
  {
    "cardId": "1-4-058",
    "hp": 89,
    "atk": 66,
    "def_": 35,
    "spAtk": 66,
    "spDef": 35,
    "spd": 70
  },
  {
    "cardId": "1-4-059",
    "hp": 136,
    "atk": 37,
    "def_": 63,
    "spAtk": 110,
    "spDef": 48,
    "spd": 48
  },
  {
    "cardId": "1-4-060",
    "hp": 57,
    "atk": 20,
    "def_": 28,
    "spAtk": 34,
    "spDef": 32,
    "spd": 25
  },
  {
    "cardId": "1-4-061",
    "hp": 91,
    "atk": 35,
    "def_": 54,
    "spAtk": 70,
    "spDef": 60,
    "spd": 42
  },
  {
    "cardId": "1-4-062",
    "hp": 104,
    "atk": 37,
    "def_": 63,
    "spAtk": 84,
    "spDef": 88,
    "spd": 124
  },
  {
    "cardId": "1-4-063",
    "hp": 62,
    "atk": 45,
    "def_": 31,
    "spAtk": 25,
    "spDef": 20,
    "spd": 20
  },
  {
    "cardId": "1-4-064",
    "hp": 124,
    "atk": 37,
    "def_": 81,
    "spAtk": 65,
    "spDef": 50,
    "spd": 50
  },
  {
    "cardId": "1-4-065",
    "hp": 63,
    "atk": 119,
    "def_": 75,
    "spAtk": 66,
    "spDef": 57,
    "spd": 75
  },
  {
    "cardId": "1-4-066",
    "hp": 59,
    "atk": 37,
    "def_": 31,
    "spAtk": 27,
    "spDef": 24,
    "spd": 25
  },
  {
    "cardId": "1-4-067",
    "hp": 90,
    "atk": 37,
    "def_": 64,
    "spAtk": 57,
    "spDef": 44,
    "spd": 45
  },
  {
    "cardId": "1-4-068",
    "hp": 117,
    "atk": 73,
    "def_": 64,
    "spAtk": 67,
    "spDef": 62,
    "spd": 110
  },
  {
    "cardId": "1-4-069",
    "hp": 33,
    "atk": 56,
    "def_": 37,
    "spAtk": 63,
    "spDef": 20,
    "spd": 23
  },
  {
    "cardId": "1-4-070",
    "hp": 120,
    "atk": 62,
    "def_": 70,
    "spAtk": 84,
    "spDef": 70,
    "spd": 105
  },
  {
    "cardId": "1-4-071",
    "hp": 109,
    "atk": 85,
    "def_": 85,
    "spAtk": 166,
    "spDef": 166,
    "spd": 38
  },
  {
    "cardId": "1-4-072",
    "hp": 162,
    "atk": 175,
    "def_": 120,
    "spAtk": 85,
    "spDef": 120,
    "spd": 153
  },
  {
    "cardId": "1-4-073",
    "hp": 162,
    "atk": 135,
    "def_": 150,
    "spAtk": 85,
    "spDef": 150,
    "spd": 133
  },
  {
    "cardId": "R-1-1",
    "hp": 113,
    "atk": 113,
    "def_": 113,
    "spAtk": 113,
    "spDef": 71,
    "spd": 71
  },
  {
    "cardId": "R-1-2",
    "hp": 110,
    "atk": 30,
    "def_": 97,
    "spAtk": 63,
    "spDef": 101,
    "spd": 63
  },
  {
    "cardId": "R-1-3",
    "hp": 30,
    "atk": 95,
    "def_": 58,
    "spAtk": 58,
    "spDef": 95,
    "spd": 29
  }
]