{
  "_generated_at": "2026-07-18T08:23:37.187337",
  "generation": "galaxy2",
  "cassette": 11,
  "source": "AGY/Gemini VLM v2 (two-pass: front+back)",
  "total_cards": 73,
  "errors": [],
  "cards": [
    {
      "cardId": "2-2-001",
      "diskCode": "2-2-001",
      "name": "蒼響",
      "series": "銀河第二彈",
      "stars": 6,
      "type1": "妖精",
      "type2": "鋼",
      "moveName": "巨獸斬",
      "moveType": "鋼",
      "moveCategory": "D",
      "move2Name": "月亮之力",
      "move2Type": "妖精",
      "move2Category": "X",
      "hp": 194,
      "attack": 226,
      "defense": 154,
      "spAtk": 109,
      "spDef": 154,
      "speed": 197,
      "layout": "horizontal",
      "frontPhoto": "/cards/11/2-2-001.png",
      "needsStats": false,
      "_meta": {
        "source": "agy_gemini_vlm_v2",
        "front_model": "flash",
        "back_model": "flash",
        "front_fallback": null,
        "back_fallback": null,
        "timestamp": "2026-07-17T22:10:36.051277",
        "hp_front": 206,
        "hasSuperStar": true,
        "hasGigantamax": false
      },
      "ability": "不撓之劍",
      "abilityEn": "intrepid-sword"
    },
    {
      "cardId": "2-2-002",
      "diskCode": "2-2-002",
      "name": "藏瑪然特",
      "series": "銀河第二彈",
      "stars": 6,
      "type1": "格鬥",
      "type2": "鋼",
      "moveName": "巨獸彈",
      "moveType": "鋼",
      "moveCategory": "D",
      "move2Name": "近身戰",
      "move2Type": "格鬥",
      "move2Category": "D",
      "hp": 194,
      "attack": 174,
      "defense": 193,
      "spAtk": 109,
      "spDef": 193,
      "speed": 171,
      "layout": "horizontal",
      "frontPhoto": "/cards/11/2-2-002.png",
      "needsStats": false,
      "_meta": {
        "source": "agy_gemini_vlm_v2",
        "front_model": "flash",
        "back_model": "flash",
        "front_fallback": null,
        "back_fallback": null,
        "timestamp": "2026-07-17T22:16:54.529259",
        "hp_front": 206,
        "hasSuperStar": true,
        "hasGigantamax": true
      },
      "ability": "不屈之盾",
      "abilityEn": "dauntless-shield"
    },
    {
      "cardId": "2-2-003",
      "diskCode": "2-2-003",
      "name": "鋁鋼龍",
      "series": "銀河第二彈",
      "stars": 6,
      "type1": "鋼",
      "type2": "龍",
      "moveName": "逆鱗",
      "moveType": "龍",
      "moveCategory": "D",
      "move2Name": "超極巨劣化衰變",
      "move2Type": "龍",
      "move2Category": "X",
      "hp": 166,
      "attack": 128,
      "defense": 154,
      "spAtk": 161,
      "spDef": 70,
      "speed": 115,
      "layout": "horizontal",
      "frontPhoto": "/cards/11/2-2-003.png",
      "needsStats": false,
      "_meta": {
        "source": "agy_gemini_vlm_v2",
        "front_model": "flash",
        "back_model": "flash",
        "front_fallback": null,
        "back_fallback": null,
        "timestamp": "2026-07-17T22:19:29.281441",
        "hp_front": 158,
        "hasSuperStar": true,
        "hasGigantamax": true
      },
      "ability": "輕金屬",
      "abilityEn": "light-metal"
    },
    {
      "cardId": "2-2-004",
      "diskCode": "2-2-004",
      "name": "噴火龍",
      "series": "銀河第二彈",
      "stars": 6,
      "type1": "火",
      "type2": "飛行",
      "moveName": "噴射火焰",
      "moveType": "火",
      "moveCategory": "X",
      "move2Name": "超極巨地獄滅焰",
      "move2Type": "火",
      "move2Category": "X",
      "hp": 166,
      "attack": 107,
      "defense": 100,
      "spAtk": 137,
      "spDef": 108,
      "speed": 127,
      "layout": "horizontal",
      "frontPhoto": "/cards/11/2-2-004.png",
      "needsStats": false,
      "_meta": {
        "source": "agy_gemini_vlm_v2",
        "front_model": "flash",
        "back_model": "flash",
        "front_fallback": null,
        "back_fallback": null,
        "timestamp": "2026-07-17T22:21:57.250691",
        "hp_front": 150,
        "hasSuperStar": true,
        "hasGigantamax": true
      },
      "ability": "猛火",
      "abilityEn": "blaze"
    },
    {
      "cardId": "2-2-005",
      "diskCode": "2-2-005",
      "name": "薩戮德",
      "series": "銀河第二彈",
      "stars": 6,
      "type1": "惡",
      "type2": "草",
      "moveName": "強力鞭打",
      "moveType": "草",
      "moveCategory": "D",
      "move2Name": "極巨草原",
      "move2Type": "草",
      "move2Category": "D",
      "hp": 199,
      "attack": 151,
      "defense": 133,
      "spAtk": 90,
      "spDef": 120,
      "speed": 133,
      "layout": "horizontal",
      "frontPhoto": "/cards/11/2-2-005.png",
      "needsStats": false,
      "_meta": {
        "source": "agy_gemini_vlm_v2",
        "front_model": "flash",
        "back_model": "flash",
        "front_fallback": null,
        "back_fallback": null,
        "timestamp": "2026-07-17T22:23:06.948169",
        "hp_front": 166,
        "hasSuperStar": true,
        "hasGigantamax": true
      },
      "ability": "葉子防守",
      "abilityEn": "leaf-guard"
    },
    {
      "cardId": "2-2-006",
      "diskCode": "2-2-006",
      "name": "路卡利歐",
      "series": "銀河第二彈",
      "stars": 6,
      "type1": "格鬥",
      "type2": "鋼",
      "moveName": "真氣彈",
      "moveType": "格鬥",
      "moveCategory": "X",
      "move2Name": "極巨拳門",
      "move2Type": "格鬥",
      "move2Category": "X",
      "hp": 156,
      "attack": 139,
      "defense": 90,
      "spAtk": 145,
      "spDef": 90,
      "speed": 114,
      "layout": "horizontal",
      "frontPhoto": "/cards/11/2-2-006.png",
      "needsStats": false,
      "_meta": {
        "source": "agy_gemini_vlm_v2",
        "front_model": "flash",
        "back_model": "flash",
        "front_fallback": null,
        "back_fallback": null,
        "timestamp": "2026-07-17T22:24:42.084801",
        "hp_front": 146,
        "hasSuperStar": true,
        "hasGigantamax": true
      },
      "ability": "不屈之心",
      "abilityEn": "steadfast"
    },
    {
      "cardId": "2-2-007",
      "diskCode": "2-2-007",
      "name": "烈空坐",
      "series": "銀河第二彈",
      "stars": 6,
      "type1": "龍",
      "type2": "飛行",
      "moveName": "畫龍點睛",
      "moveType": "飛行",
      "moveCategory": "D",
      "move2Name": null,
      "move2Type": null,
      "move2Category": null,
      "hp": 199,
      "attack": 188,
      "defense": 114,
      "spAtk": 188,
      "spDef": 114,
      "speed": 120,
      "layout": "horizontal",
      "frontPhoto": "/cards/11/2-2-007.png",
      "needsStats": false,
      "_meta": {
        "source": "agy_gemini_vlm_v2",
        "front_model": "flash",
        "back_model": "flash",
        "front_fallback": null,
        "back_fallback": null,
        "timestamp": "2026-07-17T22:26:17.477614",
        "hp_front": 184,
        "hasSuperStar": true,
        "hasGigantamax": false
      },
      "ability": "氣閘",
      "abilityEn": "air-lock"
    },
    {
      "cardId": "2-2-008",
      "diskCode": "2-2-008",
      "name": "拉帝亞斯",
      "series": "銀河第二彈",
      "stars": 6,
      "type1": "龍",
      "type2": "超能力",
      "moveName": "薄霧球",
      "moveType": "超能力",
      "moveCategory": "X",
      "move2Name": null,
      "move2Type": null,
      "move2Category": null,
      "hp": 166,
      "attack": 101,
      "defense": 113,
      "spAtk": 137,
      "spDef": 161,
      "speed": 137,
      "layout": "horizontal",
      "frontPhoto": "/cards/11/2-2-008.png",
      "needsStats": false,
      "_meta": {
        "source": "agy_gemini_vlm_v2",
        "front_model": "flash",
        "back_model": "flash",
        "front_fallback": null,
        "back_fallback": null,
        "timestamp": "2026-07-17T22:27:31.381851",
        "hp_front": 164,
        "hasSuperStar": true,
        "hasGigantamax": false
      },
      "ability": "飄浮",
      "abilityEn": "levitate"
    },
    {
      "cardId": "2-2-009",
      "diskCode": "2-2-009",
      "name": "拉帝歐斯",
      "series": "銀河第二彈",
      "stars": 6,
      "type1": "龍",
      "type2": "超能力",
      "moveName": "潔淨光芒",
      "moveType": "超能力",
      "moveCategory": "X",
      "move2Name": null,
      "move2Type": null,
      "move2Category": null,
      "hp": 166,
      "attack": 113,
      "defense": 101,
      "spAtk": 161,
      "spDef": 137,
      "speed": 137,
      "layout": "horizontal",
      "frontPhoto": "/cards/11/2-2-009.png",
      "needsStats": false,
      "_meta": {
        "source": "agy_gemini_vlm_v2",
        "front_model": "flash",
        "back_model": "flash",
        "front_fallback": null,
        "back_fallback": null,
        "timestamp": "2026-07-17T22:28:45.733379",
        "hp_front": 164,
        "hasSuperStar": true,
        "hasGigantamax": false
      },
      "ability": "飄浮",
      "abilityEn": "levitate"
    },
    {
      "cardId": "2-2-010",
      "diskCode": "2-2-010",
      "name": "四顎針龍",
      "series": "銀河第二彈",
      "stars": 6,
      "type1": "毒",
      "type2": "龍",
      "moveName": "毒液衝擊",
      "moveType": "毒",
      "moveCategory": "X",
      "move2Name": null,
      "move2Type": null,
      "move2Category": null,
      "hp": 160,
      "attack": 94,
      "defense": 94,
      "spAtk": 159,
      "spDef": 94,
      "speed": 152,
      "layout": "horizontal",
      "frontPhoto": "/cards/11/2-2-010.png",
      "needsStats": false,
      "_meta": {
        "source": "agy_gemini_vlm_v2",
        "front_model": "flash",
        "back_model": "flash",
        "front_fallback": null,
        "back_fallback": null,
        "timestamp": "2026-07-17T22:29:47.848348",
        "hp_front": 150,
        "hasSuperStar": true,
        "hasGigantamax": false
      },
      "ability": "異獸提升",
      "abilityEn": "beast-boost"
    },
    {
      "cardId": "2-2-011",
      "diskCode": "2-2-011",
      "name": "巨金怪",
      "series": "銀河第二彈",
      "stars": 5,
      "type1": "鋼",
      "type2": "超能力",
      "moveName": "彗星拳",
      "moveType": "鋼",
      "moveCategory": "D",
      "move2Name": null,
      "move2Type": null,
      "move2Category": null,
      "hp": 147,
      "attack": 148,
      "defense": 142,
      "spAtk": 105,
      "spDef": 100,
      "speed": 79,
      "layout": "horizontal",
      "frontPhoto": "/cards/11/2-2-011.png",
      "needsStats": false,
      "_meta": {
        "source": "agy_gemini_vlm_v2",
        "front_model": "flash",
        "back_model": "flash",
        "front_fallback": null,
        "back_fallback": null,
        "timestamp": "2026-07-17T22:30:27.605023",
        "hp_front": 144,
        "hasSuperStar": false,
        "hasGigantamax": false
      },
      "ability": "恆淨之軀",
      "abilityEn": "clear-body"
    },
    {
      "cardId": "2-2-012",
      "diskCode": "2-2-012",
      "name": "雙斧戰龍",
      "series": "銀河第二彈",
      "stars": 5,
      "type1": "龍",
      "type2": null,
      "moveName": "逆鱗",
      "moveType": "龍",
      "moveCategory": "D",
      "move2Name": "究極巨龍震天地",
      "move2Type": "龍",
      "move2Category": "D",
      "hp": 143,
      "attack": 160,
      "defense": 100,
      "spAtk": 68,
      "spDef": 79,
      "speed": 107,
      "layout": "horizontal",
      "frontPhoto": "/cards/11/2-2-012.png",
      "needsStats": false,
      "_meta": {
        "source": "agy_gemini_vlm_v2",
        "front_model": "flash",
        "back_model": "flash",
        "front_fallback": null,
        "back_fallback": null,
        "timestamp": "2026-07-17T22:31:54.670264",
        "hp_front": 132,
        "hasSuperStar": false,
        "hasGigantamax": false
      },
      "ability": "鬥爭心",
      "abilityEn": "rivalry"
    },
    {
      "cardId": "2-2-013",
      "diskCode": "2-2-013",
      "name": "化石翼龍",
      "series": "銀河第二彈",
      "stars": 5,
      "type1": "岩石",
      "type2": "飛行",
      "moveName": "飛翔",
      "moveType": "飛行",
      "moveCategory": "D",
      "move2Name": "極速俯衝轟烈撞",
      "move2Type": "飛行",
      "move2Category": "D",
      "hp": 150,
      "attack": 118,
      "defense": 75,
      "spAtk": 69,
      "spDef": 86,
      "speed": 145,
      "layout": "horizontal",
      "frontPhoto": "/cards/11/2-2-013.png",
      "needsStats": false,
      "_meta": {
        "source": "agy_gemini_vlm_v2",
        "front_model": "flash",
        "back_model": "flash",
        "front_fallback": null,
        "back_fallback": null,
        "timestamp": "2026-07-17T22:33:14.113911",
        "hp_front": 128,
        "hasSuperStar": false,
        "hasGigantamax": false
      },
      "ability": "堅硬腦袋",
      "abilityEn": "rock-head"
    },
    {
      "cardId": "2-2-014",
      "diskCode": "2-2-014",
      "name": "雷鳥龍",
      "series": "銀河第二彈",
      "stars": 5,
      "type1": "電",
      "type2": "龍",
      "moveName": "打雷",
      "moveType": "電",
      "moveCategory": "X",
      "move2Name": "極巨閃電",
      "move2Type": "電",
      "move2Category": "X",
      "hp": 175,
      "attack": 123,
      "defense": 111,
      "spAtk": 99,
      "spDef": 87,
      "speed": 93,
      "layout": "horizontal",
      "frontPhoto": "/cards/11/2-2-014.png",
      "needsStats": false,
      "_meta": {
        "source": "agy_gemini_vlm_v2",
        "front_model": "flash",
        "back_model": "flash",
        "front_fallback": null,
        "back_fallback": null,
        "timestamp": "2026-07-17T22:34:42.513466",
        "hp_front": 138,
        "hasSuperStar": false,
        "hasGigantamax": true
      },
      "ability": "蓄電",
      "abilityEn": "volt-absorb"
    },
    {
      "cardId": "2-2-015",
      "diskCode": "2-2-015",
      "name": "鰓魚龍",
      "series": "銀河第二彈",
      "stars": 5,
      "type1": "水",
      "type2": "龍",
      "moveName": "逆鱗",
      "moveType": "龍",
      "moveCategory": "D",
      "move2Name": "極巨龍騎",
      "move2Type": "龍",
      "move2Category": "D",
      "hp": 175,
      "attack": 111,
      "defense": 123,
      "spAtk": 87,
      "spDef": 99,
      "speed": 93,
      "layout": "horizontal",
      "frontPhoto": "/cards/11/2-2-015.png",
      "needsStats": false,
      "_meta": {
        "source": "agy_gemini_vlm_v2",
        "front_model": "flash",
        "back_model": "flash",
        "front_fallback": null,
        "back_fallback": null,
        "timestamp": "2026-07-17T22:36:15.091546",
        "hp_front": 138,
        "hasSuperStar": false,
        "hasGigantamax": true
      },
      "ability": "儲水",
      "abilityEn": "water-absorb"
    },
    {
      "cardId": "2-2-016",
      "diskCode": "2-2-016",
      "name": "胡地",
      "series": "銀河第二彈",
      "stars": 5,
      "type1": "超能力",
      "type2": null,
      "moveName": "精神強念",
      "moveType": "超能力",
      "moveCategory": "X",
      "move2Name": "極巨超能",
      "move2Type": "超能力",
      "move2Category": "X",
      "hp": 125,
      "attack": 60,
      "defense": 54,
      "spAtk": 153,
      "spDef": 109,
      "speed": 137,
      "layout": "horizontal",
      "frontPhoto": "/cards/11/2-2-016.png",
      "needsStats": false,
      "_meta": {
        "source": "agy_gemini_vlm_v2",
        "front_model": "flash",
        "back_model": "flash",
        "front_fallback": null,
        "back_fallback": null,
        "timestamp": "2026-07-17T22:38:31.032963",
        "hp_front": 128,
        "hasSuperStar": false,
        "hasGigantamax": true
      },
      "ability": "同步",
      "abilityEn": "synchronize"
    },
    {
      "cardId": "2-2-017",
      "diskCode": "2-2-017",
      "name": "雷鳥海獸",
      "series": "銀河第二彈",
      "stars": 5,
      "type1": "電",
      "type2": "冰",
      "moveName": "暴風雪",
      "moveType": "冰",
      "moveCategory": "X",
      "move2Name": null,
      "move2Type": null,
      "move2Category": null,
      "hp": 172,
      "attack": 121,
      "defense": 109,
      "spAtk": 109,
      "spDef": 97,
      "speed": 68,
      "layout": "horizontal",
      "frontPhoto": "/cards/11/2-2-017.png",
      "needsStats": false,
      "_meta": {
        "source": "agy_gemini_vlm_v2",
        "front_model": "flash",
        "back_model": "flash",
        "front_fallback": null,
        "back_fallback": null,
        "timestamp": "2026-07-17T22:40:07.238955",
        "hp_front": 136,
        "hasSuperStar": false,
        "hasGigantamax": false
      },
      "ability": "蓄電",
      "abilityEn": "volt-absorb"
    },
    {
      "cardId": "2-2-018",
      "diskCode": "2-2-018",
      "name": "具甲武者",
      "series": "銀河第二彈",
      "stars": 5,
      "type1": "蟲",
      "type2": "水",
      "moveName": "迎頭一擊",
      "moveType": "蟲",
      "moveCategory": "D",
      "move2Name": null,
      "move2Type": null,
      "move2Category": null,
      "hp": 145,
      "attack": 140,
      "defense": 156,
      "spAtk": 69,
      "spDef": 102,
      "speed": 48,
      "layout": "horizontal",
      "frontPhoto": "/cards/11/2-2-018.png",
      "needsStats": false,
      "_meta": {
        "source": "agy_gemini_vlm_v2",
        "front_model": "flash",
        "back_model": "flash",
        "front_fallback": null,
        "back_fallback": null,
        "timestamp": "2026-07-17T22:40:58.351126",
        "hp_front": 132,
        "hasSuperStar": false,
        "hasGigantamax": false
      },
      "ability": "不屈之心",
      "abilityEn": "steadfast"
    },
    {
      "cardId": "2-2-019",
      "diskCode": "2-2-019",
      "name": "君主蛇",
      "series": "銀河第二彈",
      "stars": 5,
      "type1": "草",
      "type2": null,
      "moveName": "飛葉風暴",
      "moveType": "草",
      "moveCategory": "X",
      "move2Name": null,
      "move2Type": null,
      "move2Category": null,
      "hp": 157,
      "attack": 93,
      "defense": 117,
      "spAtk": 93,
      "spDef": 117,
      "speed": 138,
      "layout": "vertical",
      "frontPhoto": "/cards/11/2-2-019.png",
      "needsStats": false,
      "_meta": {
        "source": "agy_gemini_vlm_v2",
        "front_model": "flash",
        "back_model": "flash",
        "front_fallback": null,
        "back_fallback": null,
        "timestamp": "2026-07-17T22:41:47.324937",
        "hp_front": 144,
        "hasSuperStar": false,
        "hasGigantamax": false
      },
      "ability": "茂盛",
      "abilityEn": "overgrow"
    },
    {
      "cardId": "2-2-020",
      "diskCode": "2-2-020",
      "name": "炎武王",
      "series": "銀河第二彈",
      "stars": 5,
      "type1": "火",
      "type2": "格鬥",
      "moveName": "閃焰衝鋒",
      "moveType": "火",
      "moveCategory": "D",
      "move2Name": null,
      "move2Type": null,
      "move2Category": null,
      "hp": 198,
      "attack": 150,
      "defense": 81,
      "spAtk": 123,
      "spDef": 81,
      "speed": 81,
      "layout": "vertical",
      "frontPhoto": "/cards/11/2-2-020.png",
      "needsStats": false,
      "_meta": {
        "source": "agy_gemini_vlm_v2",
        "front_model": "flash",
        "back_model": "flash",
        "front_fallback": null,
        "back_fallback": null,
        "timestamp": "2026-07-17T22:42:29.744022",
        "hp_front": 144,
        "hasSuperStar": false,
        "hasGigantamax": false
      },
      "ability": "猛火",
      "abilityEn": "blaze"
    },
    {
      "cardId": "2-2-021",
      "diskCode": "2-2-021",
      "name": "大劍鬼",
      "series": "銀河第二彈",
      "stars": 5,
      "type1": "水",
      "type2": null,
      "moveName": "水炮",
      "moveType": "水",
      "moveCategory": "X",
      "move2Name": null,
      "move2Type": null,
      "move2Category": null,
      "hp": 181,
      "attack": 123,
      "defense": 105,
      "spAtk": 132,
      "spDef": 87,
      "speed": 87,
      "layout": "vertical",
      "frontPhoto": "/cards/11/2-2-021.png",
      "needsStats": false,
      "_meta": {
        "source": "agy_gemini_vlm_v2",
        "front_model": "flash",
        "back_model": "flash",
        "front_fallback": null,
        "back_fallback": null,
        "timestamp": "2026-07-17T22:43:36.489114",
        "hp_front": 144,
        "hasSuperStar": false,
        "hasGigantamax": false
      },
      "ability": "激流",
      "abilityEn": "torrent"
    },
    {
      "cardId": "2-2-022",
      "diskCode": "2-2-022",
      "name": "鐵轍跡",
      "series": "銀河第二彈",
      "stars": 5,
      "type1": "地面",
      "type2": "鋼",
      "moveName": "地震",
      "moveType": "地面",
      "moveCategory": "D",
      "move2Name": null,
      "move2Type": null,
      "move2Category": null,
      "hp": 169,
      "attack": 132,
      "defense": 141,
      "spAtk": 87,
      "spDef": 84,
      "speed": 125,
      "layout": "horizontal",
      "frontPhoto": "/cards/11/2-2-022.png",
      "needsStats": false,
      "_meta": {
        "source": "agy_gemini_vlm_v2",
        "front_model": "flash",
        "back_model": "flash",
        "front_fallback": null,
        "back_fallback": null,
        "timestamp": "2026-07-17T22:45:20.793054",
        "hp_front": 148,
        "hasSuperStar": false,
        "hasGigantamax": false
      },
      "ability": "夸克充能",
      "abilityEn": "quark-drive"
    },
    {
      "cardId": "2-2-023",
      "diskCode": "2-2-023",
      "name": "毒貝比",
      "series": "銀河第二彈",
      "stars": 5,
      "type1": "毒",
      "type2": null,
      "moveName": "龍之波動",
      "moveType": "龍",
      "moveCategory": "X",
      "move2Name": null,
      "move2Type": null,
      "move2Category": null,
      "hp": 138,
      "attack": 85,
      "defense": 78,
      "spAtk": 85,
      "spDef": 78,
      "speed": 85,
      "layout": "horizontal",
      "frontPhoto": "/cards/11/2-2-023.png",
      "needsStats": false,
      "_meta": {
        "source": "agy_gemini_vlm_v2",
        "front_model": "flash",
        "back_model": "flash",
        "front_fallback": null,
        "back_fallback": null,
        "timestamp": "2026-07-17T22:46:12.790749",
        "hp_front": 110,
        "hasSuperStar": false,
        "hasGigantamax": false
      },
      "ability": "異獸提升",
      "abilityEn": "beast-boost"
    },
    {
      "cardId": "2-2-024",
      "diskCode": "2-2-024",
      "name": "布莉姆溫",
      "series": "銀河第二彈",
      "stars": 5,
      "type1": "超能力",
      "type2": "妖精",
      "moveName": "魔法閃耀",
      "moveType": "妖精",
      "moveCategory": "X",
      "move2Name": null,
      "move2Type": null,
      "move2Category": null,
      "hp": 125,
      "attack": 102,
      "defense": 107,
      "spAtk": 151,
      "spDef": 116,
      "speed": 36,
      "layout": "horizontal",
      "frontPhoto": "/cards/11/2-2-024.png",
      "needsStats": false,
      "_meta": {
        "source": "agy_gemini_vlm_v2",
        "front_model": "flash",
        "back_model": "flash",
        "front_fallback": null,
        "back_fallback": null,
        "timestamp": "2026-07-17T22:47:11.272620",
        "hp_front": 128,
        "hasSuperStar": false,
        "hasGigantamax": false
      },
      "ability": "治癒之心",
      "abilityEn": "healer"
    },
    {
      "cardId": "2-2-025",
      "diskCode": "2-2-025",
      "name": "阿勃梭魯",
      "series": "銀河第二彈",
      "stars": 5,
      "type1": "惡",
      "type2": null,
      "moveName": "地獄突刺",
      "moveType": "惡",
      "moveCategory": "D",
      "move2Name": null,
      "move2Type": null,
      "move2Category": null,
      "hp": 148,
      "attack": 161,
      "defense": 77,
      "spAtk": 95,
      "spDef": 77,
      "speed": 95,
      "layout": "horizontal",
      "frontPhoto": "/cards/11/2-2-025.png",
      "needsStats": false,
      "_meta": {
        "source": "agy_gemini_vlm_v2",
        "front_model": "flash",
        "back_model": "flash",
        "front_fallback": null,
        "back_fallback": null,
        "timestamp": "2026-07-17T22:47:47.692541",
        "hp_front": 130,
        "hasSuperStar": false,
        "hasGigantamax": false
      },
      "ability": "壓迫感",
      "abilityEn": "pressure"
    },
    {
      "cardId": "2-2-026",
      "diskCode": "2-2-026",
      "name": "蒂蕾喵",
      "series": "銀河第二彈",
      "stars": 3,
      "type1": "草",
      "type2": null,
      "moveName": "魔法葉",
      "moveType": "草",
      "moveCategory": "X",
      "move2Name": null,
      "move2Type": null,
      "move2Category": null,
      "hp": 103,
      "attack": 72,
      "defense": 57,
      "spAtk": 55,
      "spDef": 57,
      "speed": 74,
      "layout": "vertical",
      "frontPhoto": "/cards/11/2-2-026.png",
      "needsStats": false,
      "_meta": {
        "source": "agy_gemini_vlm_v2",
        "front_model": "flash",
        "back_model": "flash",
        "front_fallback": null,
        "back_fallback": null,
        "timestamp": "2026-07-17T22:48:43.094131",
        "hp_front": 84,
        "hasSuperStar": false,
        "hasGigantamax": false
      },
      "ability": "茂盛",
      "abilityEn": "overgrow"
    },
    {
      "cardId": "2-2-027",
      "diskCode": "2-2-027",
      "name": "魔幻假面喵",
      "series": "銀河第二彈",
      "stars": 4,
      "type1": "草",
      "type2": "惡",
      "moveName": "暗襲要害",
      "moveType": "惡",
      "moveCategory": "D",
      "move2Name": null,
      "move2Type": null,
      "move2Category": null,
      "hp": 130,
      "attack": 110,
      "defense": 72,
      "spAtk": 82,
      "spDef": 72,
      "speed": 123,
      "layout": "vertical",
      "frontPhoto": "/cards/11/2-2-027.png",
      "needsStats": false,
      "_meta": {
        "source": "agy_gemini_vlm_v2",
        "front_model": "flash",
        "back_model": "flash",
        "front_fallback": null,
        "back_fallback": null,
        "timestamp": "2026-07-17T22:49:29.631175",
        "hp_front": 118,
        "hasSuperStar": false,
        "hasGigantamax": false
      },
      "ability": "茂盛",
      "abilityEn": "overgrow"
    },
    {
      "cardId": "2-2-028",
      "diskCode": "2-2-028",
      "name": "炙燙鱷",
      "series": "銀河第二彈",
      "stars": 3,
      "type1": "火",
      "type2": null,
      "moveName": "燒盡",
      "moveType": "火",
      "moveCategory": "X",
      "move2Name": null,
      "move2Type": null,
      "move2Category": null,
      "hp": 120,
      "attack": 51,
      "defense": 70,
      "spAtk": 80,
      "spDef": 53,
      "speed": 46,
      "layout": "vertical",
      "frontPhoto": "/cards/11/2-2-028.png",
      "needsStats": false,
      "_meta": {
        "source": "agy_gemini_vlm_v2",
        "front_model": "flash",
        "back_model": "flash",
        "front_fallback": null,
        "back_fallback": null,
        "timestamp": "2026-07-17T22:50:10.867529",
        "hp_front": 84,
        "hasSuperStar": false,
        "hasGigantamax": false
      },
      "ability": "猛火",
      "abilityEn": "blaze"
    },
    {
      "cardId": "2-2-029",
      "diskCode": "2-2-029",
      "name": "骨紋巨聲鱷",
      "series": "銀河第二彈",
      "stars": 4,
      "type1": "火",
      "type2": "幽靈",
      "moveName": "禍不單行",
      "moveType": "幽靈",
      "moveCategory": "X",
      "move2Name": null,
      "move2Type": null,
      "move2Category": null,
      "hp": 157,
      "attack": 77,
      "defense": 101,
      "spAtk": 110,
      "spDef": 77,
      "speed": 68,
      "layout": "vertical",
      "frontPhoto": "/cards/11/2-2-029.png",
      "needsStats": false,
      "_meta": {
        "source": "agy_gemini_vlm_v2",
        "front_model": "flash",
        "back_model": "flash",
        "front_fallback": null,
        "back_fallback": null,
        "timestamp": "2026-07-17T22:51:11.390296",
        "hp_front": 118,
        "hasSuperStar": false,
        "hasGigantamax": false
      },
      "ability": "龐克搖滾",
      "abilityEn": "punk-rock"
    },
    {
      "cardId": "2-2-030",
      "diskCode": "2-2-030",
      "name": "湧躍鴨",
      "series": "銀河第二彈",
      "stars": 3,
      "type1": "水",
      "type2": null,
      "moveName": "水之波動",
      "moveType": "水",
      "moveCategory": "X",
      "move2Name": null,
      "move2Type": null,
      "move2Category": null,
      "hp": 110,
      "attack": 76,
      "defense": 59,
      "spAtk": 59,
      "spDef": 55,
      "speed": 59,
      "layout": "vertical",
      "frontPhoto": "/cards/11/2-2-030.png",
      "needsStats": false,
      "_meta": {
        "source": "agy_gemini_vlm_v2",
        "front_model": "flash",
        "back_model": "flash",
        "front_fallback": null,
        "back_fallback": null,
        "timestamp": "2026-07-17T22:51:52.179393",
        "hp_front": 84,
        "hasSuperStar": false,
        "hasGigantamax": false
      },
      "ability": "激流",
      "abilityEn": "torrent"
    },
    {
      "cardId": "2-2-031",
      "diskCode": "2-2-031",
      "name": "狂歡浪舞鴨",
      "series": "銀河第二彈",
      "stars": 4,
      "type1": "水",
      "type2": "格鬥",
      "moveName": "下盤踢",
      "moveType": "格鬥",
      "moveCategory": "D",
      "move2Name": null,
      "move2Type": null,
      "move2Category": null,
      "hp": 139,
      "attack": 120,
      "defense": 81,
      "spAtk": 86,
      "spDef": 77,
      "speed": 86,
      "layout": "vertical",
      "frontPhoto": "/cards/11/2-2-031.png",
      "needsStats": false,
      "_meta": {
        "source": "agy_gemini_vlm_v2",
        "front_model": "flash",
        "back_model": "flash",
        "front_fallback": null,
        "back_fallback": null,
        "timestamp": "2026-07-17T22:52:31.406980",
        "hp_front": 118,
        "hasSuperStar": false,
        "hasGigantamax": false
      },
      "ability": "激流",
      "abilityEn": "torrent"
    },
    {
      "cardId": "2-2-032",
      "diskCode": "2-2-032",
      "name": "藤藤蛇",
      "series": "銀河第二彈",
      "stars": 2,
      "type1": "草",
      "type2": null,
      "moveName": "藤鞭",
      "moveType": "草",
      "moveCategory": "D",
      "move2Name": null,
      "move2Type": null,
      "move2Category": null,
      "hp": 61,
      "attack": 29,
      "defense": 34,
      "spAtk": 29,
      "spDef": 34,
      "speed": 39,
      "layout": "vertical",
      "frontPhoto": "/cards/11/2-2-032.png",
      "needsStats": false,
      "_meta": {
        "source": "agy_gemini_vlm_v2",
        "front_model": "flash",
        "back_model": "flash",
        "front_fallback": null,
        "back_fallback": null,
        "timestamp": "2026-07-17T22:53:30.902384",
        "hp_front": 46,
        "hasSuperStar": false,
        "hasGigantamax": false
      },
      "ability": "茂盛",
      "abilityEn": "overgrow"
    },
    {
      "cardId": "2-2-033",
      "diskCode": "2-2-033",
      "name": "青藤蛇",
      "series": "銀河第二彈",
      "stars": 3,
      "type1": "草",
      "type2": null,
      "moveName": "超級吸取",
      "moveType": "草",
      "moveCategory": "X",
      "move2Name": null,
      "move2Type": null,
      "move2Category": null,
      "hp": 102,
      "attack": 55,
      "defense": 68,
      "spAtk": 55,
      "spDef": 68,
      "speed": 74,
      "layout": "vertical",
      "frontPhoto": "/cards/11/2-2-033.png",
      "needsStats": false,
      "_meta": {
        "source": "agy_gemini_vlm_v2",
        "front_model": "flash",
        "back_model": "flash",
        "front_fallback": null,
        "back_fallback": null,
        "timestamp": "2026-07-17T22:55:00.312349",
        "hp_front": 84,
        "hasSuperStar": false,
        "hasGigantamax": false
      },
      "ability": "茂盛",
      "abilityEn": "overgrow"
    },
    {
      "cardId": "2-2-034",
      "diskCode": "2-2-034",
      "name": "君主蛇",
      "series": "銀河第二彈",
      "stars": 4,
      "type1": "草",
      "type2": null,
      "moveName": "青草攪拌器",
      "moveType": "草",
      "moveCategory": "X",
      "move2Name": null,
      "move2Type": null,
      "move2Category": null,
      "hp": 130,
      "attack": 77,
      "defense": 96,
      "spAtk": 77,
      "spDef": 96,
      "speed": 113,
      "layout": "vertical",
      "frontPhoto": "/cards/11/2-2-034.png",
      "needsStats": false,
      "_meta": {
        "source": "agy_gemini_vlm_v2",
        "front_model": "flash",
        "back_model": "flash",
        "front_fallback": null,
        "back_fallback": null,
        "timestamp": "2026-07-17T22:56:23.629079",
        "hp_front": 118,
        "hasSuperStar": false,
        "hasGigantamax": false
      },
      "ability": "茂盛",
      "abilityEn": "overgrow"
    },
    {
      "cardId": "2-2-035",
      "diskCode": "2-2-035",
      "name": "暖暖豬",
      "series": "銀河第二彈",
      "stars": 2,
      "type1": "火",
      "type2": null,
      "moveName": "火花",
      "moveType": "火",
      "moveCategory": "X",
      "move2Name": null,
      "move2Type": null,
      "move2Category": null,
      "hp": 72,
      "attack": 39,
      "defense": 29,
      "spAtk": 29,
      "spDef": 29,
      "speed": 29,
      "layout": "vertical",
      "frontPhoto": "/cards/11/2-2-035.png",
      "needsStats": false,
      "_meta": {
        "source": "agy_gemini_vlm_v2",
        "front_model": "flash",
        "back_model": "flash",
        "front_fallback": null,
        "back_fallback": null,
        "timestamp": "2026-07-17T22:57:01.707803",
        "hp_front": 46,
        "hasSuperStar": false,
        "hasGigantamax": false
      },
      "ability": "猛火",
      "abilityEn": "blaze"
    },
    {
      "cardId": "2-2-036",
      "diskCode": "2-2-036",
      "name": "炒炒豬",
      "series": "銀河第二彈",
      "stars": 3,
      "type1": "火",
      "type2": "格鬥",
      "moveName": "蓄能焰襲",
      "moveType": "火",
      "moveCategory": "D",
      "move2Name": null,
      "move2Type": null,
      "move2Category": null,
      "hp": 127,
      "attack": 83,
      "defense": 51,
      "spAtk": 63,
      "spDef": 51,
      "speed": 51,
      "layout": "vertical",
      "frontPhoto": "/cards/11/2-2-036.png",
      "needsStats": false,
      "_meta": {
        "source": "agy_gemini_vlm_v2",
        "front_model": "flash",
        "back_model": "flash",
        "front_fallback": null,
        "back_fallback": null,
        "timestamp": "2026-07-17T22:58:22.625333",
        "hp_front": 86,
        "hasSuperStar": false,
        "hasGigantamax": false
      },
      "ability": "猛火",
      "abilityEn": "blaze"
    },
    {
      "cardId": "2-2-037",
      "diskCode": "2-2-037",
      "name": "炎武王",
      "series": "銀河第二彈",
      "stars": 4,
      "type1": "火",
      "type2": "格鬥",
      "moveName": "火焰拳",
      "moveType": "火",
      "moveCategory": "D",
      "move2Name": null,
      "move2Type": null,
      "move2Category": null,
      "hp": 163,
      "attack": 123,
      "defense": 67,
      "spAtk": 101,
      "spDef": 67,
      "speed": 67,
      "layout": "vertical",
      "frontPhoto": "/cards/11/2-2-037.png",
      "needsStats": false,
      "_meta": {
        "source": "agy_gemini_vlm_v2",
        "front_model": "flash",
        "back_model": "flash",
        "front_fallback": null,
        "back_fallback": null,
        "timestamp": "2026-07-17T22:59:44.234992",
        "hp_front": 118,
        "hasSuperStar": false,
        "hasGigantamax": false
      },
      "ability": "猛火",
      "abilityEn": "blaze"
    },
    {
      "cardId": "2-2-038",
      "diskCode": "2-2-038",
      "name": "水水獺",
      "series": "銀河第二彈",
      "stars": 2,
      "type1": "水",
      "type2": null,
      "moveName": "水流噴射",
      "moveType": "水",
      "moveCategory": "X",
      "move2Name": null,
      "move2Type": null,
      "move2Category": null,
      "hp": 66,
      "attack": 34,
      "defense": 29,
      "spAtk": 39,
      "spDef": 29,
      "speed": 29,
      "layout": "vertical",
      "frontPhoto": "/cards/11/2-2-038.png",
      "needsStats": false,
      "_meta": {
        "source": "agy_gemini_vlm_v2",
        "front_model": "flash",
        "back_model": "flash",
        "front_fallback": null,
        "back_fallback": null,
        "timestamp": "2026-07-17T23:00:51.624689",
        "hp_front": 46,
        "hasSuperStar": false,
        "hasGigantamax": false
      },
      "ability": "激流",
      "abilityEn": "torrent"
    },
    {
      "cardId": "2-2-039",
      "diskCode": "2-2-039",
      "name": "雙刃丸",
      "series": "銀河第二彈",
      "stars": 3,
      "type1": "水",
      "type2": null,
      "moveName": "水之波動",
      "moveType": "水",
      "moveCategory": "X",
      "move2Name": null,
      "move2Type": null,
      "move2Category": null,
      "hp": 115,
      "attack": 68,
      "defense": 55,
      "spAtk": 74,
      "spDef": 55,
      "speed": 55,
      "layout": "vertical",
      "frontPhoto": "/cards/11/2-2-039.png",
      "needsStats": false,
      "_meta": {
        "source": "agy_gemini_vlm_v2",
        "front_model": "flash",
        "back_model": "flash",
        "front_fallback": null,
        "back_fallback": null,
        "timestamp": "2026-07-17T23:01:51.241625",
        "hp_front": 84,
        "hasSuperStar": false,
        "hasGigantamax": false
      },
      "ability": "激流",
      "abilityEn": "torrent"
    },
    {
      "cardId": "2-2-040",
      "diskCode": "2-2-040",
      "name": "大劍鬼",
      "series": "銀河第二彈",
      "stars": 4,
      "type1": "水",
      "type2": null,
      "moveName": "貝殼刃",
      "moveType": "水",
      "moveCategory": "D",
      "move2Name": null,
      "move2Type": null,
      "move2Category": null,
      "hp": 149,
      "attack": 101,
      "defense": 86,
      "spAtk": 108,
      "spDef": 72,
      "speed": 72,
      "layout": "vertical",
      "frontPhoto": "/cards/11/2-2-040.png",
      "needsStats": false,
      "_meta": {
        "source": "agy_gemini_vlm_v2",
        "front_model": "flash",
        "back_model": "flash",
        "front_fallback": null,
        "back_fallback": null,
        "timestamp": "2026-07-17T23:02:56.781882",
        "hp_front": 118,
        "hasSuperStar": false,
        "hasGigantamax": false
      },
      "ability": "激流",
      "abilityEn": "torrent"
    },
    {
      "cardId": "2-2-041",
      "diskCode": "2-2-041",
      "name": "蚊香蝌蚪",
      "series": "銀河第二彈",
      "stars": 2,
      "type1": "水",
      "type2": null,
      "moveName": "水槍",
      "moveType": "水",
      "moveCategory": "X",
      "move2Name": null,
      "move2Type": null,
      "move2Category": null,
      "hp": 56,
      "attack": 31,
      "defense": 25,
      "spAtk": 25,
      "spDef": 25,
      "speed": 51,
      "layout": "vertical",
      "frontPhoto": "/cards/11/2-2-041.png",
      "needsStats": false,
      "_meta": {
        "source": "agy_gemini_vlm_v2",
        "front_model": "flash",
        "back_model": "flash",
        "front_fallback": null,
        "back_fallback": null,
        "timestamp": "2026-07-17T23:04:09.809274",
        "hp_front": 42,
        "hasSuperStar": false,
        "hasGigantamax": false
      },
      "ability": "儲水",
      "abilityEn": "water-absorb"
    },
    {
      "cardId": "2-2-042",
      "diskCode": "2-2-042",
      "name": "蚊香君",
      "series": "銀河第二彈",
      "stars": 3,
      "type1": "水",
      "type2": null,
      "moveName": "泡沫光線",
      "moveType": "水",
      "moveCategory": "X",
      "move2Name": null,
      "move2Type": null,
      "move2Category": null,
      "hp": 99,
      "attack": 55,
      "defense": 55,
      "spAtk": 44,
      "spDef": 44,
      "speed": 75,
      "layout": "vertical",
      "frontPhoto": "/cards/11/2-2-042.png",
      "needsStats": false,
      "_meta": {
        "source": "agy_gemini_vlm_v2",
        "front_model": "flash",
        "back_model": "flash",
        "front_fallback": null,
        "back_fallback": null,
        "timestamp": "2026-07-17T23:05:14.834361",
        "hp_front": 74,
        "hasSuperStar": false,
        "hasGigantamax": false
      },
      "ability": "儲水",
      "abilityEn": "water-absorb"
    },
    {
      "cardId": "2-2-043",
      "diskCode": "2-2-043",
      "name": "蚊香泳士",
      "series": "銀河第二彈",
      "stars": 4,
      "type1": "水",
      "type2": "格鬥",
      "moveName": "地獄翻滾",
      "moveType": "格鬥",
      "moveCategory": "D",
      "move2Name": null,
      "move2Type": null,
      "move2Category": null,
      "hp": 136,
      "attack": 90,
      "defense": 90,
      "spAtk": 68,
      "spDef": 86,
      "speed": 68,
      "layout": "vertical",
      "frontPhoto": "/cards/11/2-2-043.png",
      "needsStats": false,
      "_meta": {
        "source": "agy_gemini_vlm_v2",
        "front_model": "flash",
        "back_model": "flash",
        "front_fallback": null,
        "back_fallback": null,
        "timestamp": "2026-07-17T23:05:53.638098",
        "hp_front": 108,
        "hasSuperStar": false,
        "hasGigantamax": false
      },
      "ability": "儲水",
      "abilityEn": "water-absorb"
    },
    {
      "cardId": "2-2-044",
      "diskCode": "2-2-044",
      "name": "醜醜魚",
      "series": "銀河第二彈",
      "stars": 2,
      "type1": "水",
      "type2": null,
      "moveName": "撞擊",
      "moveType": "一般",
      "moveCategory": "D",
      "move2Name": null,
      "move2Type": null,
      "move2Category": null,
      "hp": 46,
      "attack": 12,
      "defense": 15,
      "spAtk": 10,
      "spDef": 33,
      "speed": 46,
      "layout": "vertical",
      "frontPhoto": "/cards/11/2-2-044.png",
      "needsStats": false,
      "_meta": {
        "source": "agy_gemini_vlm_v2",
        "front_model": "flash",
        "back_model": "flash",
        "front_fallback": null,
        "back_fallback": null,
        "timestamp": "2026-07-17T23:06:39.161638",
        "hp_front": 32,
        "hasSuperStar": false,
        "hasGigantamax": false
      },
      "ability": "悠游自如",
      "abilityEn": "swift-swim"
    },
    {
      "cardId": "2-2-045",
      "diskCode": "2-2-045",
      "name": "美納斯",
      "series": "銀河第二彈",
      "stars": 4,
      "type1": "水",
      "type2": null,
      "moveName": "攀瀑",
      "moveType": "水",
      "moveCategory": "D",
      "move2Name": null,
      "move2Type": null,
      "move2Category": null,
      "hp": 140,
      "attack": 59,
      "defense": 76,
      "spAtk": 95,
      "spDef": 117,
      "speed": 77,
      "layout": "vertical",
      "frontPhoto": "/cards/11/2-2-045.png",
      "needsStats": false,
      "_meta": {
        "source": "agy_gemini_vlm_v2",
        "front_model": "flash",
        "back_model": "flash",
        "front_fallback": null,
        "back_fallback": null,
        "timestamp": "2026-07-17T23:07:53.571207",
        "hp_front": 112,
        "hasSuperStar": false,
        "hasGigantamax": false
      },
      "ability": "神奇鱗片",
      "abilityEn": "marvel-scale"
    },
    {
      "cardId": "2-2-046",
      "diskCode": "2-2-046",
      "name": "麻麻小魚",
      "series": "銀河第二彈",
      "stars": 2,
      "type1": "電",
      "type2": null,
      "moveName": "充電光束",
      "moveType": "電",
      "moveCategory": "X",
      "move2Name": null,
      "move2Type": null,
      "move2Category": null,
      "hp": 55,
      "attack": 34,
      "defense": 26,
      "spAtk": 29,
      "spDef": 26,
      "speed": 37,
      "layout": "vertical",
      "frontPhoto": "/cards/11/2-2-046.png",
      "needsStats": false,
      "_meta": {
        "source": "agy_gemini_vlm_v2",
        "front_model": "flash",
        "back_model": "flash",
        "front_fallback": null,
        "back_fallback": null,
        "timestamp": "2026-07-17T23:09:48.723455",
        "hp_front": 42,
        "hasSuperStar": false,
        "hasGigantamax": false
      },
      "ability": "飄浮",
      "abilityEn": "levitate"
    },
    {
      "cardId": "2-2-047",
      "diskCode": "2-2-047",
      "name": "麻麻鰻",
      "series": "銀河第二彈",
      "stars": 3,
      "type1": "電",
      "type2": null,
      "moveName": "電擊波",
      "moveType": "電",
      "moveCategory": "X",
      "move2Name": null,
      "move2Type": null,
      "move2Category": null,
      "hp": 104,
      "attack": 74,
      "defense": 62,
      "spAtk": 66,
      "spDef": 62,
      "speed": 37,
      "layout": "vertical",
      "frontPhoto": "/cards/11/2-2-047.png",
      "needsStats": false,
      "_meta": {
        "source": "agy_gemini_vlm_v2",
        "front_model": "flash",
        "back_model": "flash",
        "front_fallback": null,
        "back_fallback": null,
        "timestamp": "2026-07-17T23:10:32.957181",
        "hp_front": 82,
        "hasSuperStar": false,
        "hasGigantamax": false
      },
      "ability": "飄浮",
      "abilityEn": "levitate"
    },
    {
      "cardId": "2-2-048",
      "diskCode": "2-2-048",
      "name": "麻麻鰻魚王",
      "series": "銀河第二彈",
      "stars": 4,
      "type1": "電",
      "type2": null,
      "moveName": "伏特替換",
      "moveType": "電",
      "moveCategory": "X",
      "move2Name": null,
      "move2Type": null,
      "move2Category": null,
      "hp": 136,
      "attack": 113,
      "defense": 80,
      "spAtk": 103,
      "spDef": 80,
      "speed": 52,
      "layout": "vertical",
      "frontPhoto": "/cards/11/2-2-048.png",
      "needsStats": false,
      "_meta": {
        "source": "agy_gemini_vlm_v2",
        "front_model": "flash",
        "back_model": "flash",
        "front_fallback": null,
        "back_fallback": null,
        "timestamp": "2026-07-17T23:11:16.276507",
        "hp_front": 112,
        "hasSuperStar": false,
        "hasGigantamax": false
      },
      "ability": "飄浮",
      "abilityEn": "levitate"
    },
    {
      "cardId": "2-2-049",
      "diskCode": "2-2-049",
      "name": "拉魯拉絲",
      "series": "銀河第二彈",
      "stars": 2,
      "type1": "超能力",
      "type2": "妖精",
      "moveName": "念力",
      "moveType": "超能力",
      "moveCategory": "X",
      "move2Name": null,
      "move2Type": null,
      "move2Category": null,
      "hp": 52,
      "attack": 18,
      "defense": 18,
      "spAtk": 29,
      "spDef": 23,
      "speed": 26,
      "layout": "vertical",
      "frontPhoto": "/cards/11/2-2-049.png",
      "needsStats": false,
      "_meta": {
        "source": "agy_gemini_vlm_v2",
        "front_model": "flash",
        "back_model": "flash",
        "front_fallback": null,
        "back_fallback": null,
        "timestamp": "2026-07-17T23:12:35.931500",
        "hp_front": 34,
        "hasSuperStar": false,
        "hasGigantamax": false
      },
      "ability": "同步",
      "abilityEn": "synchronize"
    },
    {
      "cardId": "2-2-050",
      "diskCode": "2-2-050",
      "name": "奇魯莉安",
      "series": "銀河第二彈",
      "stars": 3,
      "type1": "超能力",
      "type2": "妖精",
      "moveName": "幻象光線",
      "moveType": "超能力",
      "moveCategory": "X",
      "move2Name": null,
      "move2Type": null,
      "move2Category": null,
      "hp": 82,
      "attack": 33,
      "defense": 33,
      "spAtk": 58,
      "spDef": 50,
      "speed": 46,
      "layout": "vertical",
      "frontPhoto": "/cards/11/2-2-050.png",
      "needsStats": false,
      "_meta": {
        "source": "agy_gemini_vlm_v2",
        "front_model": "flash",
        "back_model": "flash",
        "front_fallback": null,
        "back_fallback": null,
        "timestamp": "2026-07-17T23:13:19.114713",
        "hp_front": 60,
        "hasSuperStar": false,
        "hasGigantamax": false
      },
      "ability": "同步",
      "abilityEn": "synchronize"
    },
    {
      "cardId": "2-2-051",
      "diskCode": "2-2-051",
      "name": "沙奈朵",
      "series": "銀河第二彈",
      "stars": 4,
      "type1": "超能力",
      "type2": "妖精",
      "moveName": "精神強念",
      "moveType": "超能力",
      "moveCategory": "X",
      "move2Name": null,
      "move2Type": null,
      "move2Category": null,
      "hp": 120,
      "attack": 66,
      "defense": 66,
      "spAtk": 122,
      "spDef": 113,
      "speed": 80,
      "layout": "vertical",
      "frontPhoto": "/cards/11/2-2-051.png",
      "needsStats": false,
      "_meta": {
        "source": "agy_gemini_vlm_v2",
        "front_model": "flash",
        "back_model": "flash",
        "front_fallback": null,
        "back_fallback": null,
        "timestamp": "2026-07-17T23:13:56.141023",
        "hp_front": 114,
        "hasSuperStar": false,
        "hasGigantamax": false
      },
      "ability": "同步",
      "abilityEn": "synchronize"
    },
    {
      "cardId": "2-2-052",
      "diskCode": "2-2-052",
      "name": "艾路雷朵",
      "series": "銀河第二彈",
      "stars": 4,
      "type1": "超能力",
      "type2": "格鬥",
      "moveName": "劈瓦",
      "moveType": "格鬥",
      "moveCategory": "D",
      "move2Name": null,
      "move2Type": null,
      "move2Category": null,
      "hp": 120,
      "attack": 122,
      "defense": 66,
      "spAtk": 66,
      "spDef": 113,
      "speed": 80,
      "layout": "vertical",
      "frontPhoto": "/cards/11/2-2-052.png",
      "needsStats": false,
      "_meta": {
        "source": "agy_gemini_vlm_v2",
        "front_model": "flash",
        "back_model": "flash",
        "front_fallback": null,
        "back_fallback": null,
        "timestamp": "2026-07-17T23:14:36.928327",
        "hp_front": 114,
        "hasSuperStar": false,
        "hasGigantamax": false
      },
      "ability": "不屈之心",
      "abilityEn": "steadfast"
    },
    {
      "cardId": "2-2-053",
      "diskCode": "2-2-053",
      "name": "百足蜈蚣",
      "series": "銀河第二彈",
      "stars": 2,
      "type1": "蟲",
      "type2": "毒",
      "moveName": "毒針",
      "moveType": "毒",
      "moveCategory": "D",
      "move2Name": null,
      "move2Type": null,
      "move2Category": null,
      "hp": 53,
      "attack": 29,
      "defense": 36,
      "spAtk": 21,
      "spDef": 26,
      "speed": 35,
      "layout": "vertical",
      "frontPhoto": "/cards/11/2-2-053.png",
      "needsStats": false,
      "_meta": {
        "source": "agy_gemini_vlm_v2",
        "front_model": "flash",
        "back_model": "flash",
        "front_fallback": null,
        "back_fallback": null,
        "timestamp": "2026-07-17T23:15:47.710127",
        "hp_front": 40,
        "hasSuperStar": false,
        "hasGigantamax": false
      },
      "ability": "毒刺",
      "abilityEn": "poison-point"
    },
    {
      "cardId": "2-2-054",
      "diskCode": "2-2-054",
      "name": "車輪毬",
      "series": "銀河第二彈",
      "stars": 3,
      "type1": "蟲",
      "type2": "毒",
      "moveName": "蟲咬",
      "moveType": "蟲",
      "moveCategory": "D",
      "move2Name": null,
      "move2Type": null,
      "move2Category": null,
      "hp": 85,
      "attack": 51,
      "defense": 88,
      "spAtk": 38,
      "spDef": 71,
      "speed": 44,
      "layout": "vertical",
      "frontPhoto": "/cards/11/2-2-054.png",
      "needsStats": false,
      "_meta": {
        "source": "agy_gemini_vlm_v2",
        "front_model": "flash",
        "back_model": "flash",
        "front_fallback": null,
        "back_fallback": null,
        "timestamp": "2026-07-17T23:16:39.716599",
        "hp_front": 76,
        "hasSuperStar": false,
        "hasGigantamax": false
      },
      "ability": "毒刺",
      "abilityEn": "poison-point"
    },
    {
      "cardId": "2-2-055",
      "diskCode": "2-2-055",
      "name": "蜈蚣王",
      "series": "銀河第二彈",
      "stars": 4,
      "type1": "蟲",
      "type2": "毒",
      "moveName": "十字毒刃",
      "moveType": "毒",
      "moveCategory": "D",
      "move2Name": null,
      "move2Type": null,
      "move2Category": null,
      "hp": 115,
      "attack": 101,
      "defense": 90,
      "spAtk": 57,
      "spDef": 71,
      "speed": 112,
      "layout": "vertical",
      "frontPhoto": "/cards/11/2-2-055.png",
      "needsStats": false,
      "_meta": {
        "source": "agy_gemini_vlm_v2",
        "front_model": "flash",
        "back_model": "flash",
        "front_fallback": null,
        "back_fallback": null,
        "timestamp": "2026-07-17T23:17:37.567612",
        "hp_front": 110,
        "hasSuperStar": false,
        "hasGigantamax": false
      },
      "ability": "毒刺",
      "abilityEn": "poison-point"
    },
    {
      "cardId": "2-2-056",
      "diskCode": "2-2-056",
      "name": "貪心栗鼠",
      "series": "銀河第二彈",
      "stars": 2,
      "type1": "一般",
      "type2": null,
      "moveName": "撞擊",
      "moveType": "一般",
      "moveCategory": "D",
      "move2Name": null,
      "move2Type": null,
      "move2Category": null,
      "hp": 72,
      "attack": 33,
      "defense": 33,
      "spAtk": 23,
      "spDef": 23,
      "speed": 18,
      "layout": "vertical",
      "frontPhoto": "/cards/11/2-2-056.png",
      "needsStats": false,
      "_meta": {
        "source": "agy_gemini_vlm_v2",
        "front_model": "flash",
        "back_model": "flash",
        "front_fallback": null,
        "back_fallback": null,
        "timestamp": "2026-07-17T23:18:33.776645",
        "hp_front": 40,
        "hasSuperStar": false,
        "hasGigantamax": false
      },
      "ability": "頰囊",
      "abilityEn": "cheek-pouch"
    },
    {
      "cardId": "2-2-057",
      "diskCode": "2-2-057",
      "name": "藏飽栗鼠",
      "series": "銀河第二彈",
      "stars": 4,
      "type1": "一般",
      "type2": null,
      "moveName": "渴望",
      "moveType": "一般",
      "moveCategory": "D",
      "move2Name": null,
      "move2Type": null,
      "move2Category": null,
      "hp": 163,
      "attack": 90,
      "defense": 90,
      "spAtk": 54,
      "spDef": 72,
      "speed": 23,
      "layout": "vertical",
      "frontPhoto": "/cards/11/2-2-057.png",
      "needsStats": false,
      "_meta": {
        "source": "agy_gemini_vlm_v2",
        "front_model": "flash",
        "back_model": "flash",
        "front_fallback": false,
        "back_fallback": false,
        "timestamp": "2026-07-18T08:06:03.344119",
        "hp_front": 98,
        "hasSuperStar": false,
        "hasGigantamax": false
      },
      "ability": "頰囊",
      "abilityEn": "cheek-pouch"
    },
    {
      "cardId": "2-2-058",
      "diskCode": "2-2-058",
      "name": "海豹球",
      "series": "銀河第二彈",
      "stars": 2,
      "type1": "冰",
      "type2": "水",
      "moveName": "細雪",
      "moveType": "冰",
      "moveCategory": "X",
      "move2Name": null,
      "move2Type": null,
      "move2Category": null,
      "hp": 74,
      "attack": 26,
      "defense": 32,
      "spAtk": 34,
      "spDef": 32,
      "speed": 18,
      "layout": "vertical",
      "frontPhoto": "/cards/11/2-2-058.png",
      "needsStats": false,
      "_meta": {
        "source": "agy_gemini_vlm_v2",
        "front_model": "flash",
        "back_model": "flash",
        "front_fallback": false,
        "back_fallback": false,
        "timestamp": "2026-07-18T08:07:17.718829",
        "hp_front": 44,
        "hasSuperStar": false,
        "hasGigantamax": false
      },
      "ability": "厚脂肪",
      "abilityEn": "thick-fat"
    },
    {
      "cardId": "2-2-059",
      "diskCode": "2-2-059",
      "name": "海魔獅",
      "series": "銀河第二彈",
      "stars": 3,
      "type1": "冰",
      "type2": "水",
      "moveName": "冰凍之風",
      "moveType": "冰",
      "moveCategory": "X",
      "move2Name": null,
      "move2Type": null,
      "move2Category": null,
      "hp": 124,
      "attack": 54,
      "defense": 62,
      "spAtk": 66,
      "spDef": 62,
      "speed": 41,
      "layout": "vertical",
      "frontPhoto": "/cards/11/2-2-059.png",
      "needsStats": false,
      "_meta": {
        "source": "agy_gemini_vlm_v2",
        "front_model": "flash",
        "back_model": "flash",
        "front_fallback": false,
        "back_fallback": false,
        "timestamp": "2026-07-18T08:07:48.774560",
        "hp_front": 82,
        "hasSuperStar": false,
        "hasGigantamax": false
      },
      "ability": "厚脂肪",
      "abilityEn": "thick-fat"
    },
    {
      "cardId": "2-2-060",
      "diskCode": "2-2-060",
      "name": "帝牙海獅",
      "series": "銀河第二彈",
      "stars": 4,
      "type1": "冰",
      "type2": "水",
      "moveName": "極光束",
      "moveType": "冰",
      "moveCategory": "X",
      "move2Name": null,
      "move2Type": null,
      "move2Category": null,
      "hp": 160,
      "attack": 80,
      "defense": 89,
      "spAtk": 94,
      "spDef": 89,
      "speed": 66,
      "layout": "vertical",
      "frontPhoto": "/cards/11/2-2-060.png",
      "needsStats": false,
      "_meta": {
        "source": "agy_gemini_vlm_v2",
        "front_model": "flash",
        "back_model": "flash",
        "front_fallback": false,
        "back_fallback": false,
        "timestamp": "2026-07-18T08:08:32.020745",
        "hp_front": 116,
        "hasSuperStar": false,
        "hasGigantamax": false
      },
      "ability": "厚脂肪",
      "abilityEn": "thick-fat"
    },
    {
      "cardId": "2-2-061",
      "diskCode": "2-2-061",
      "name": "含羞苞",
      "series": "銀河第二彈",
      "stars": 2,
      "type1": "草",
      "type2": "毒",
      "moveName": "吸取",
      "moveType": "草",
      "moveCategory": "X",
      "move2Name": null,
      "move2Type": null,
      "move2Category": null,
      "hp": 56,
      "attack": 20,
      "defense": 23,
      "spAtk": 31,
      "spDef": 41,
      "speed": 33,
      "layout": "vertical",
      "frontPhoto": "/cards/11/2-2-061.png",
      "needsStats": false,
      "_meta": {
        "source": "agy_gemini_vlm_v2",
        "front_model": "flash",
        "back_model": "flash",
        "front_fallback": false,
        "back_fallback": false,
        "timestamp": "2026-07-18T08:09:07.388365",
        "hp_front": 40,
        "hasSuperStar": false,
        "hasGigantamax": false
      },
      "ability": "自然回復",
      "abilityEn": "natural-cure"
    },
    {
      "cardId": "2-2-062",
      "diskCode": "2-2-062",
      "name": "毒薔薇",
      "series": "銀河第二彈",
      "stars": 3,
      "type1": "草",
      "type2": "毒",
      "moveName": "超級吸取",
      "moveType": "草",
      "moveCategory": "X",
      "move2Name": null,
      "move2Type": null,
      "move2Category": null,
      "hp": 88,
      "attack": 51,
      "defense": 40,
      "spAtk": 83,
      "spDef": 67,
      "speed": 55,
      "layout": "vertical",
      "frontPhoto": "/cards/11/2-2-062.png",
      "needsStats": false,
      "_meta": {
        "source": "agy_gemini_vlm_v2",
        "front_model": "flash",
        "back_model": "flash",
        "front_fallback": false,
        "back_fallback": false,
        "timestamp": "2026-07-18T08:10:02.377586",
        "hp_front": 76,
        "hasSuperStar": false,
        "hasGigantamax": false
      },
      "ability": "自然回復",
      "abilityEn": "natural-cure"
    },
    {
      "cardId": "2-2-063",
      "diskCode": "2-2-063",
      "name": "羅絲雷朵",
      "series": "銀河第二彈",
      "stars": 4,
      "type1": "草",
      "type2": "毒",
      "moveName": "魔法葉",
      "moveType": "草",
      "moveCategory": "X",
      "move2Name": null,
      "move2Type": null,
      "move2Category": null,
      "hp": 109,
      "attack": 68,
      "defense": 63,
      "spAtk": 117,
      "spDef": 99,
      "speed": 86,
      "layout": "vertical",
      "frontPhoto": "/cards/11/2-2-063.png",
      "needsStats": false,
      "_meta": {
        "source": "agy_gemini_vlm_v2",
        "front_model": "flash",
        "back_model": "flash",
        "front_fallback": false,
        "back_fallback": false,
        "timestamp": "2026-07-18T08:10:40.619470",
        "hp_front": 108,
        "hasSuperStar": false,
        "hasGigantamax": false
      },
      "ability": "自然回復",
      "abilityEn": "natural-cure"
    },
    {
      "cardId": "2-2-064",
      "diskCode": "2-2-064",
      "name": "小仙奶",
      "series": "銀河第二彈",
      "stars": 2,
      "type1": "妖精",
      "type2": null,
      "moveName": "吸取之吻",
      "moveType": "妖精",
      "moveCategory": "X",
      "move2Name": null,
      "move2Type": null,
      "move2Category": null,
      "hp": 61,
      "attack": 26,
      "defense": 26,
      "spAtk": 32,
      "spDef": 37,
      "speed": 23,
      "layout": "vertical",
      "frontPhoto": "/cards/11/2-2-064.png",
      "needsStats": false,
      "_meta": {
        "source": "agy_gemini_vlm_v2",
        "front_model": "flash",
        "back_model": "flash",
        "front_fallback": false,
        "back_fallback": false,
        "timestamp": "2026-07-18T08:11:16.769615",
        "hp_front": 42,
        "hasSuperStar": false,
        "hasGigantamax": false
      },
      "ability": "甜幕",
      "abilityEn": "sweet-veil"
    },
    {
      "cardId": "2-2-065",
      "diskCode": "2-2-065",
      "name": "霜奶仙",
      "series": "銀河第二彈",
      "stars": 4,
      "type1": "妖精",
      "type2": null,
      "moveName": "吸取之吻",
      "moveType": "妖精",
      "moveCategory": "X",
      "move2Name": null,
      "move2Type": null,
      "move2Category": null,
      "hp": 120,
      "attack": 62,
      "defense": 77,
      "spAtk": 110,
      "spDef": 121,
      "speed": 66,
      "layout": "vertical",
      "frontPhoto": "/cards/11/2-2-065.png",
      "needsStats": false,
      "_meta": {
        "source": "agy_gemini_vlm_v2",
        "front_model": "flash",
        "back_model": "flash",
        "front_fallback": false,
        "back_fallback": false,
        "timestamp": "2026-07-18T08:11:48.410320",
        "hp_front": 112,
        "hasSuperStar": false,
        "hasGigantamax": false
      },
      "ability": "甜幕",
      "abilityEn": "sweet-veil"
    },
    {
      "cardId": "2-2-066",
      "diskCode": "2-2-066",
      "name": "電擊怪",
      "series": "銀河第二彈",
      "stars": 2,
      "type1": "電",
      "type2": null,
      "moveName": "電擊",
      "moveType": "電",
      "moveCategory": "X",
      "move2Name": null,
      "move2Type": null,
      "move2Category": null,
      "hp": 61,
      "attack": 39,
      "defense": 24,
      "spAtk": 40,
      "spDef": 34,
      "speed": 56,
      "layout": "vertical",
      "frontPhoto": "/cards/11/2-2-066.png",
      "needsStats": false,
      "_meta": {
        "source": "agy_gemini_vlm_v2",
        "front_model": "flash",
        "back_model": "flash",
        "front_fallback": false,
        "back_fallback": false,
        "timestamp": "2026-07-18T08:12:28.336982",
        "hp_front": 50,
        "hasSuperStar": false,
        "hasGigantamax": false
      },
      "ability": "靜電",
      "abilityEn": "static"
    },
    {
      "cardId": "2-2-067",
      "diskCode": "2-2-067",
      "name": "電擊獸",
      "series": "銀河第二彈",
      "stars": 3,
      "type1": "電",
      "type2": null,
      "moveName": "電擊波",
      "moveType": "電",
      "moveCategory": "X",
      "move2Name": null,
      "move2Type": null,
      "move2Category": null,
      "hp": 104,
      "attack": 152,
      "defense": 73,
      "spAtk": 51,
      "spDef": 74,
      "speed": 82,
      "layout": "vertical",
      "frontPhoto": "/cards/11/2-2-067.png",
      "needsStats": false,
      "_meta": {
        "source": "agy_gemini_vlm_v2",
        "front_model": "flash",
        "back_model": "flash",
        "front_fallback": false,
        "back_fallback": false,
        "timestamp": "2026-07-18T08:14:32.094268",
        "hp_front": 96,
        "hasSuperStar": false,
        "hasGigantamax": false
      },
      "ability": "靜電",
      "abilityEn": "static"
    },
    {
      "cardId": "2-2-068",
      "diskCode": "2-2-068",
      "name": "電擊魔獸",
      "series": "銀河第二彈",
      "stars": 4,
      "type1": "電",
      "type2": null,
      "moveName": "雷電拳",
      "moveType": "電",
      "moveCategory": "D",
      "move2Name": null,
      "move2Type": null,
      "move2Category": null,
      "hp": 127,
      "attack": 120,
      "defense": 67,
      "spAtk": 94,
      "spDef": 84,
      "speed": 94,
      "layout": "vertical",
      "frontPhoto": "/cards/11/2-2-068.png",
      "needsStats": false,
      "_meta": {
        "source": "agy_gemini_vlm_v2",
        "front_model": "flash",
        "back_model": "flash",
        "front_fallback": false,
        "back_fallback": false,
        "timestamp": "2026-07-18T08:15:28.467627",
        "hp_front": 118,
        "hasSuperStar": false,
        "hasGigantamax": false
      },
      "ability": "電氣引擎",
      "abilityEn": "motor-drive"
    },
    {
      "cardId": "2-2-069",
      "diskCode": "2-2-069",
      "name": "伽勒爾喵喵",
      "series": "銀河第二彈",
      "stars": 2,
      "type1": "鋼",
      "type2": null,
      "moveName": "金屬爪",
      "moveType": "鋼",
      "moveCategory": "D",
      "move2Name": null,
      "move2Type": null,
      "move2Category": null,
      "hp": 62,
      "attack": 38,
      "defense": 33,
      "spAtk": 25,
      "spDef": 25,
      "speed": 25,
      "layout": "vertical",
      "frontPhoto": "/cards/11/2-2-069.png",
      "needsStats": false,
      "_meta": {
        "source": "agy_gemini_vlm_v2",
        "front_model": "flash",
        "back_model": "flash",
        "front_fallback": false,
        "back_fallback": false,
        "timestamp": "2026-07-18T08:16:04.992424",
        "hp_front": 42,
        "hasSuperStar": false,
        "hasGigantamax": false
      },
      "ability": "撿拾",
      "abilityEn": "pickup"
    },
    {
      "cardId": "2-2-070",
      "diskCode": "2-2-070",
      "name": "喵頭目",
      "series": "銀河第二彈",
      "stars": 3,
      "type1": "鋼",
      "type2": null,
      "moveName": "鐵頭",
      "moveType": "鋼",
      "moveCategory": "D",
      "move2Name": null,
      "move2Type": null,
      "move2Category": null,
      "hp": 101,
      "attack": 88,
      "defense": 81,
      "spAtk": 43,
      "spDef": 50,
      "speed": 43,
      "layout": "vertical",
      "frontPhoto": "/cards/11/2-2-070.png",
      "needsStats": false,
      "_meta": {
        "source": "agy_gemini_vlm_v2",
        "front_model": "flash",
        "back_model": "flash",
        "front_fallback": false,
        "back_fallback": false,
        "timestamp": "2026-07-18T08:17:32.661368",
        "hp_front": 82,
        "hasSuperStar": false,
        "hasGigantamax": false
      },
      "ability": "戰鬥盔甲",
      "abilityEn": "battle-armor"
    },
    {
      "cardId": "R-2-1",
      "diskCode": "R-2-1",
      "name": "皮卡丘",
      "series": "銀河第二彈",
      "stars": 0,
      "type1": "電",
      "type2": null,
      "moveName": "十萬伏特",
      "moveType": "電",
      "moveCategory": "X",
      "move2Name": "超極巨萬雷轟頂",
      "move2Type": "電",
      "move2Category": "X",
      "hp": 118,
      "attack": 75,
      "defense": 56,
      "spAtk": 69,
      "spDef": 69,
      "speed": 120,
      "layout": "vertical",
      "frontPhoto": "/cards/11/R-2-1.png",
      "needsStats": false,
      "_meta": {
        "source": "agy_gemini_vlm_v2",
        "front_model": "flash",
        "back_model": "flash",
        "front_fallback": false,
        "back_fallback": false,
        "timestamp": "2026-07-18T08:18:22.652087",
        "hp_front": 102,
        "hasSuperStar": false,
        "hasGigantamax": true
      },
      "category": "special",
      "ability": "靜電",
      "abilityEn": "static"
    },
    {
      "cardId": "R-2-2",
      "diskCode": "R-2-2",
      "name": "噴火龍",
      "series": "銀河第二彈",
      "stars": 0,
      "type1": "火",
      "type2": "飛行",
      "moveName": "噴射火焰",
      "moveType": "火",
      "moveCategory": "X",
      "move2Name": "超極巨地獄滅焰",
      "move2Type": "火",
      "move2Category": "X",
      "hp": 140,
      "attack": 90,
      "defense": 84,
      "spAtk": 116,
      "spDef": 91,
      "speed": 107,
      "layout": "vertical",
      "frontPhoto": "/cards/11/R-2-2.png",
      "needsStats": false,
      "_meta": {
        "source": "agy_gemini_vlm_v2",
        "front_model": "flash",
        "back_model": "flash",
        "front_fallback": false,
        "back_fallback": false,
        "timestamp": "2026-07-18T08:19:17.289785",
        "hp_front": 126,
        "hasSuperStar": false,
        "hasGigantamax": true
      },
      "category": "special",
      "ability": "猛火",
      "abilityEn": "blaze"
    },
    {
      "cardId": "R-2-3",
      "diskCode": "R-2-3",
      "name": "耿鬼",
      "series": "銀河第二彈",
      "stars": 0,
      "type1": "幽靈",
      "type2": "毒",
      "moveName": "暗影球",
      "moveType": "幽靈",
      "moveCategory": "X",
      "move2Name": "超極巨幻影幽魂",
      "move2Type": "幽靈",
      "move2Category": "X",
      "hp": 122,
      "attack": 71,
      "defense": 66,
      "spAtk": 137,
      "spDef": 81,
      "speed": 117,
      "layout": "vertical",
      "frontPhoto": "/cards/11/R-2-3.png",
      "needsStats": false,
      "_meta": {
        "source": "agy_gemini_vlm_v2",
        "front_model": "flash",
        "back_model": "flash",
        "front_fallback": false,
        "back_fallback": false,
        "timestamp": "2026-07-18T08:22:39.550325",
        "hp_front": 118,
        "hasSuperStar": false,
        "hasGigantamax": true
      },
      "category": "special",
      "ability": "詛咒之軀",
      "abilityEn": "cursed-body"
    }
  ]
}